ros_rosidl_typesupport_introspection_cpp-4.9.5.data/data/include/rosidl_typesupport_introspection_cpp/rosidl_typesupport_introspection_cpp/field_types.hpp
ros_rosidl_typesupport_introspection_cpp-4.9.5.data/data/include/rosidl_typesupport_introspection_cpp/rosidl_typesupport_introspection_cpp/identifier.hpp
ros_rosidl_typesupport_introspection_cpp-4.9.5.data/data/include/rosidl_typesupport_introspection_cpp/rosidl_typesupport_introspection_cpp/message_introspection.hpp
ros_rosidl_typesupport_introspection_cpp-4.9.5.data/data/include/rosidl_typesupport_introspection_cpp/rosidl_typesupport_introspection_cpp/message_type_support_decl.hpp
ros_rosidl_typesupport_introspection_cpp-4.9.5.data/data/include/rosidl_typesupport_introspection_cpp/rosidl_typesupport_introspection_cpp/service_introspection.hpp
ros_rosidl_typesupport_introspection_cpp-4.9.5.data/data/include/rosidl_typesupport_introspection_cpp/rosidl_typesupport_introspection_cpp/service_type_support_decl.hpp
ros_rosidl_typesupport_introspection_cpp-4.9.5.data/data/include/rosidl_typesupport_introspection_cpp/rosidl_typesupport_introspection_cpp/visibility_control.h
ros_rosidl_typesupport_introspection_cpp-4.9.5.data/data/lib/librosidl_typesupport_introspection_cpp.so
ros_rosidl_typesupport_introspection_cpp-4.9.5.data/data/lib/python3.10/site-packages/rosidl_typesupport_introspection_cpp/__init__.py
ros_rosidl_typesupport_introspection_cpp-4.9.5.data/data/lib/python3.10/site-packages/rosidl_typesupport_introspection_cpp/cli.py
ros_rosidl_typesupport_introspection_cpp-4.9.5.data/data/lib/python3.10/site-packages/rosidl_typesupport_introspection_cpp/__pycache__/__init__.cpython-310.pyc
ros_rosidl_typesupport_introspection_cpp-4.9.5.data/data/lib/python3.10/site-packages/rosidl_typesupport_introspection_cpp/__pycache__/cli.cpython-310.pyc
ros_rosidl_typesupport_introspection_cpp-4.9.5.data/data/lib/python3.10/site-packages/rosidl_typesupport_introspection_cpp-4.9.5-py3.10.egg-info/PKG-INFO
ros_rosidl_typesupport_introspection_cpp-4.9.5.data/data/lib/python3.10/site-packages/rosidl_typesupport_introspection_cpp-4.9.5-py3.10.egg-info/SOURCES.txt
ros_rosidl_typesupport_introspection_cpp-4.9.5.data/data/lib/python3.10/site-packages/rosidl_typesupport_introspection_cpp-4.9.5-py3.10.egg-info/dependency_links.txt
ros_rosidl_typesupport_introspection_cpp-4.9.5.data/data/lib/python3.10/site-packages/rosidl_typesupport_introspection_cpp-4.9.5-py3.10.egg-info/entry_points.txt
ros_rosidl_typesupport_introspection_cpp-4.9.5.data/data/lib/python3.10/site-packages/rosidl_typesupport_introspection_cpp-4.9.5-py3.10.egg-info/top_level.txt
ros_rosidl_typesupport_introspection_cpp-4.9.5.data/data/lib/rosidl_typesupport_introspection_cpp/rosidl_typesupport_introspection_cpp
ros_rosidl_typesupport_introspection_cpp-4.9.5.dist-info/METADATA
ros_rosidl_typesupport_introspection_cpp-4.9.5.dist-info/WHEEL
ros_rosidl_typesupport_introspection_cpp-4.9.5.dist-info/entry_points.txt
ros_rosidl_typesupport_introspection_cpp-4.9.5.dist-info/top_level.txt
ros_rosidl_typesupport_introspection_cpp-4.9.5.dist-info/RECORD
